zenplate/__init__.py
zenplate/__main__.py
zenplate/cli.py
zenplate/config.py
zenplate/exceptions.py
zenplate/output_handler.py
zenplate/setup_logging.py
zenplate/template_data.py
zenplate/template_manager.py
zenplate/yaml_extras.py
zenplate/plugins/__init__.py
zenplate/plugins/base.py
zenplate/plugins/data_plugins.py
zenplate/plugins/jinja_plugins.py
zenplate/plugins/plugin_manager.py
zenplate/plugins/default_plugins/__init__.py
zenplate/plugins/default_plugins/data_plugins.py
zenplate/plugins/default_plugins/jinja_plugins.py
zenplate-0.1.3.dist-info/licenses/LICENSE
zenplate-0.1.3.dist-info/METADATA
zenplate-0.1.3.dist-info/WHEEL
zenplate-0.1.3.dist-info/entry_points.txt
zenplate-0.1.3.dist-info/top_level.txt
zenplate-0.1.3.dist-info/RECORD
