Metadata-Version: 2.4
Name: zenplate
Version: 0.1.3
Summary: A pluggable CLI templating tool leveraging the powers of Jinja2 and YAML
Author-email: Cam Ratchford <camratchford@gmail.com>
Project-URL: Homepage, https://github.com/camratchford/zenplate
Project-URL: Source, https://github.com/camratchford/zenplate
Classifier: Development Status :: 3 - Alpha
Classifier: Programming Language :: Python
Classifier: Programming Language :: Python :: 3 :: Only
Classifier: Intended Audience :: Developers
Classifier: Intended Audience :: Information Technology
Classifier: Intended Audience :: System Administrators
Classifier: Operating System :: POSIX :: Linux
Classifier: Environment :: Console
Classifier: Topic :: Software Development :: Build Tools
Classifier: Topic :: Utilities
Requires-Python: >=3.10
License-File: LICENSE
Requires-Dist: click==8.1.7
Requires-Dist: colorama==0.4.6
Requires-Dist: Jinja2==3.1.2
Requires-Dist: markdown-it-py==3.0.0
Requires-Dist: MarkupSafe==2.1.3
Requires-Dist: mdurl==0.1.2
Requires-Dist: Pygments==2.16.1
Requires-Dist: PyYAML==6.0.1
Requires-Dist: rich==13.6.0
Requires-Dist: shellingham==1.5.4
Requires-Dist: typer==0.15.1
Requires-Dist: typing_extensions==4.8.0
Provides-Extra: development
Requires-Dist: mkdocs; extra == "development"
Requires-Dist: mkdocs-material; extra == "development"
Requires-Dist: ruff; extra == "development"
Requires-Dist: pytest; extra == "development"
Requires-Dist: mypy; extra == "development"
Requires-Dist: pyinstaller; extra == "development"
Requires-Dist: build; extra == "development"
Requires-Dist: twine; extra == "development"
Dynamic: license-file
